affine/__init__.py
affine/tests/__init__.py
affine/tests/test_pickle.py
affine/tests/test_rotation.py
affine/tests/test_transform.py
affine-2.3.1.dist-info/AUTHORS.txt
affine-2.3.1.dist-info/LICENSE.txt
affine-2.3.1.dist-info/METADATA
affine-2.3.1.dist-info/WHEEL
affine-2.3.1.dist-info/top_level.txt
affine-2.3.1.dist-info/zip-safe
affine-2.3.1.dist-info/RECORD
