Metadata-Version: 2.1
Name: affine
Version: 2.3.1
Summary: Matrices describing affine transformation of the plane.
Home-page: https://github.com/sgillies/affine
Author: Sean Gillies
Author-email: sean@mapbox.com
License: BSD
Keywords: affine transformation matrix
Platform: UNKNOWN
Provides-Extra: test
License-File: LICENSE.txt
License-File: AUTHORS.txt
